[{
        "id": 1,
        "nomIngredient": "Poulet frit"
    },

    {
        "id": 2,
        "nomIngredient": "Steak haché"
    },

    {
        "id": 3,
        "nomIngredient": "Dinde"
    },

    {
        "id": 4,
        "nomIngredient": "Jambon"
    },

    {
        "id": 5,
        "nomIngredient": "Poisson frit"
    },

    {
        "id": 6,
        "nomIngredient": "Pain burger"
    },

    {
        "id": 7,
        "nomIngredient": "Pain de mie"
    },

    {
        "id": 8,
        "nomIngredient": "Tortilla"
    },

    {
        "id": 9,
        "nomIngredient": "Pain de mie"
    },

    {
        "id": 10,
        "nomIngredient": "Pain brioché"
    },

    {
        "id": 11,
        "nomIngredient": "Pain baguette"
    },

    {
        "id": 12,
        "nomIngredient": "Pain pita"
    },

    {
        "id": 13,
        "nomIngredient": "Oignon"
    },

    {
        "id": 14,
        "nomIngredient": "Tomate"
    },

    {
        "id": 15,
        "nomIngredient": "Salade"
    },

    {
        "id": 16,
        "nomIngredient": "Carotte"
    },

    {
        "id": 17,
        "nomIngredient": "Cheddar"
    },

    {
        "id": 18,
        "nomIngredient": "Emmental"
    },

    {
        "id": 19,
        "nomIngredient": "Chevre"
    },

    {
        "id": 20,
        "nomIngredient": "Ketchup"
    },

    {
        "id": 21,
        "nomIngredient": "Mayonnaise"
    },

    {
        "id": 22,
        "nomIngredient": "Barbecue"
    },

    {
        "id": 23,
        "nomIngredient": "Moutarde"
    },

    {
        "id": 24,
        "nomIngredient": "Oeuf"
    }

]